{
  "type": "minecraft:fishing",
  "pools": [
    {
      "rolls": 1,
      "bonus_rolls": 0,
      "entries": [
        {
          "type": "minecraft:item",
          "weight": 60,
          "name": "minecraft:cod"
        },
        {
          "type": "minecraft:item",
          "weight": 25,
          "name": "minecraft:salmon"
        },
        {
          "type": "minecraft:item",
          "weight": 2,
          "name": "minecraft:tropical_fish"
        },
        {
          "type": "minecraft:item",
          "weight": 13,
          "name": "minecraft:pufferfish"
        },
        {
          "type": "minecraft:item",
          "weight": 10,
          "name": "crabbersdelight:clam"
        },
        {
          "type": "minecraft:item",
          "weight": 10,
          "name": "crabbersdelight:raw_crab"
        },
        {
          "type": "minecraft:item",
          "weight": 10,
          "name": "crabbersdelight:raw_shrimp"
        },
        {
          "type": "minecraft:item",
          "weight": 10,
          "name": "crabbersdelight:raw_clawster"
        }
      ]
    }
  ],
  "random_sequence": "minecraft:gameplay/fishing/fish"
}
